{
    "name": "¡Bienvenido!",
    "title": "¡Bienvenido!",
    "elements": [
        {
            "type": "Text",
            "text": "¡Bienvenidos a Hoos Piensa con Calma! Esta sesión inicial será un poco más larga que las sesiones futuras. Primero se le pedirá que complete algunas encuestas sobre su salud mental y sus patrones de pensamiento. Luego, le brindaremos más información sobre el fundamento de este programa y le explicaremos cómo aprovechar al máximo la aplicación. Tendrá la oportunidad de programar una reunión con el equipo de investigación al final de esta sesión si tiene alguna pregunta o inquietud. ¿Listo para comenzar? Presione el botón Siguiente a continuación para comenzar a completar cuestionarios."
        }
    ]
}